{
  "Editor@@line-hover-indicator": true,
  "Editor@@border-focus-mode": false,
  "Components@@outline-enhanced": true,
  "Components@@extra-anim-remove": true,
  "Appearance-light@@theme-light-style-select": "theme-light-background-adapt",
  "Appearance-light@@accent-light": "#006E1B",
  "Appearance-light@@accent-color-override-light": true,
  "Appearance-light@@background-underlying-light": "#FCFDF6",
  "Appearance-light@@on-border-light": "#006E1B",
  "Appearance-light@@background-primary@@light": "#FCFDF6",
  "Appearance-light@@background-secondary@@light": "#FCFDF6",
  "Appearance-light@@background-tertiary@@light": "#FCFDF6",
  "Appearance-light@@card-shadow-light": "0px 0px 0px 1px var(--background-modifier-border)",
  "Appearance-light@@color-activated-tab-header-light": "#006E1B",
  "Appearance-light@@border-radius-activated-tab-header-light": "6px",
  "Appearance-light@@shadow-activated-tab-header-light": "0px 3px 0px var(--background-primary),0px 12px 0px -6px var(--color-accent)",
  "Mo-Table@@tbMH-qkms": "tbMH-fqk",
  "sidenote-callout@@top-sidenote-callout-title": true,
  "sidenote-callout@@sidenote-backgound": true,
  "Mo-Table@@tbMH-ds": "tbMH-ds-tm",
  "Components@@folder-font-bold": true,
  "Editor@@collapse-icon-restore": false,
  "Editor@@h2-divider-on": true,
  "Editor@@h1-divider-on": true,
  "Editor@@h1-color-select": "h1-color-default",
  "obsidian-composer-theme@@theme-variant-light": "composer--SuScheme-light",
  "pane-relief@@pane-relief-pane-numbering": true,
  "floating-toc-styles@@toggle-floating-toc-header-color": true,
  "floating-toc-styles@@floating-toc-color-h1@@light": "#F30303",
  "floating-toc-styles@@floating-toc-color-h2@@light": "#FE893E",
  "floating-toc-styles@@floating-toc-color-h3@@light": "#619300",
  "floating-toc-styles@@floating-toc-color-h5@@light": "#00C8A4",
  "floating-toc-styles@@floating-toc-color-h6@@light": "#930093",
  "floating-toc-styles@@floating-toc-remove-heading-indicator": false,
  "floating-toc-styles@@enable-outline-style": "float-outline-style",
  "floating-toc-styles@@floating-toc-color-h4@@light": "#BF24FF"
}